pysast.py
pysast-1.1.3a0.dist-info/entry_points.txt
pysast-1.1.3a0.dist-info/LICENSE
pysast-1.1.3a0.dist-info/METADATA
pysast-1.1.3a0.dist-info/WHEEL
pysast-1.1.3a0.dist-info/RECORD
